pyzooqle/__init__.py
pyzooqle/zooqle.py
pyzooqle-0.0.5.dist-info/DESCRIPTION.rst
pyzooqle-0.0.5.dist-info/METADATA
pyzooqle-0.0.5.dist-info/RECORD
pyzooqle-0.0.5.dist-info/WHEEL
pyzooqle-0.0.5.dist-info/metadata.json
pyzooqle-0.0.5.dist-info/top_level.txt
