Metadata-Version: 2.0
Name: pyzooqle
Version: 0.0.5
Summary: Python interface to https://zooqle.com
Home-page: https://github.com/srob650/pyzooqle
Author: srob650
Author-email: pytvmaze@gmail.com
License: MIT
Keywords: python zooqle torrents torrent
Platform: UNKNOWN
Classifier: Development Status :: 2 - Pre-Alpha
Classifier: Intended Audience :: Developers
Classifier: License :: OSI Approved :: MIT License
Classifier: Programming Language :: Python :: 2.7
Classifier: Programming Language :: Python :: 3.5
Requires-Dist: requests
Requires-Dist: bs4
